{
  "type": "modestmining:forging",
  "ingredients": [
    {
      "item": "minecraft:clay_ball"
    },
    {
      "item": "minecraft:clay_ball"
    },
    {
      "item": "minecraft:clay_ball"
    },
    {
      "item": "minecraft:clay_ball"
    },
    {
      "item": "modestmining:fiber"
    },
    {
      "item": "modestmining:fiber"
    },
    {
      "item": "modestmining:fiber"
    },
    {
      "item": "modestmining:fiber"
    }
  ],
  "output": {
    "item": "modestmining:adobe_brick",
    "count": 8
  }
}